brand/__init__.py
brand/base.py
brand/misc.py
brand/search_names.py
brand/util.py
brand-0.0.7.dist-info/LICENSE
brand-0.0.7.dist-info/METADATA
brand-0.0.7.dist-info/WHEEL
brand-0.0.7.dist-info/top_level.txt
brand-0.0.7.dist-info/RECORD
