Metadata-Version: 2.1
Name: brand
Version: 0.0.7
Summary: Finding available domain names
Home-page: https://github.com/thorwhalen/brand
Author: Thor Whalen
License: apache-2.0
Platform: any
License-File: LICENSE
Requires-Dist: py2store
Requires-Dist: argh
Requires-Dist: requests
Requires-Dist: lexis
